[
  {
    "code": "012205",
    "name": "계양전기우",
    "date": "2026-05-08T02:51:03.839938"
  },
  {
    "code": "000500",
    "name": "가온전선",
    "date": "2026-05-08T05:58:55.167847"
  },
  {
    "code": "307950",
    "name": "현대오토에버",
    "date": "2026-05-08T07:46:05.322659"
  },
  {
    "code": "011000",
    "name": "진원생명과학",
    "date": "2026-05-08T09:21:57.785803"
  },
  {
    "code": "006345",
    "name": "대원전선우",
    "date": "2026-05-08T11:16:14.052560"
  },
  {
    "code": "044820",
    "name": "코스맥스비티아이",
    "date": "2026-05-08T13:46:43.257506"
  },
  {
    "code": "013000",
    "name": "세우글로벌",
    "date": "2026-05-08T15:23:43.455330"
  },
  {
    "code": "004710",
    "name": "한솔테크닉스",
    "date": "2026-05-08T17:18:27.992597"
  },
  {
    "code": "002020",
    "name": "코오롱",
    "date": "2026-05-08T19:18:13.589739"
  },
  {
    "code": "018880",
    "name": "한온시스템",
    "date": "2026-05-08T21:01:12.516072"
  }
]